{
  "meta_info": {
    "selected_ticker": "AKAM",
    "selection_reason": "After yesterday's earnings announcement, plunged over 8% intraday today with a surge in volume, S&P500 hot loser.",
    "references": [
      {
        "name": "Barrons",
        "url": "https://www.barrons.com/articles/akamai-earnings-stock-price-284f54c5"
      },
      {
        "name": "Yahoo Finance",
        "url": "https://finance.yahoo.com/news/akamai-technologies-q4-earnings-call-011249913.html"
      },
      {
        "name": "TIKR",
        "url": "https://www.tikr.com/blog/akamai-technologies-stock-sinks-14-on-profit-outlook-heres-what-changed-after-q4"
      }
    ]
  },
  "seo": {
    "title": "AKAM Drops 8% After Earnings? Should You Really Sell?",
    "meta_description": "Earnings were good yesterday, so why did AKAM drop 8% today? Honest review of why the guidance was cut and what’s next.",
    "slug": "akam-earnings-drop-guidance-cut-20260223",
    "category": "Stocks | Tech | Earnings",
    "tags": [
      "AKAM",
      "Cloud Security",
      "Earnings Miss",
      "AI Inference"
    ],
    "published_date": "2026-02-23",
    "author": "Research Team"
  },
  "content": {
    "hook_summary": {
      "heading": "3-Second Investment Key Summary",
      "points": [
        "Earnings were good but 2026 guidance was cut, so it plunged 8% today.",
        "Institutions dumped shares, causing volume to explode to 10x normal levels.",
        "Better to watch now; it’s oversold but risks remain high."
      ],
      "claims": [
        {
          "what": "Stock price decline",
          "value": "-8%",
          "url": "https://www.barrons.com/articles/akamai-earnings-stock-price-284f54c5"
        }
      ]
    },
    "excerpt": "Let’s look at why AKAM dropped so much after earnings today and the chances of revaluation going forward. Earnings were good but guidance was the issue.",
    "sections": [
      {
        "type": "today_story",
        "heading": "Market today_story: Why is AKAM Moving?",
        "content": "Wow.. the market went crazy today after yesterday's earnings release, right? Earnings beat expectations, but the 2026 outlook came in below analyst estimates, so investors sold off. There’s no policy risk, but the market narrative is about intensifying competition in the cloud market.",
        "claims": [
          {
            "what": "Stock reaction",
            "value": "almost 8% fall",
            "url": "https://www.barrons.com/articles/akamai-earnings-stock-price-284f54c5"
          }
        ]
      },
      {
        "type": "price_talk",
        "heading": "Recent price talk & Momentum",
        "content": "Looking at the chart, it slightly rose after hours yesterday but started a straight drop from this morning. While the whole tech sector is shaky, AKAM was hit harder due to guidance. Seems like an overcorrection compared to the sector.",
        "claims": [
          {
            "what": "Q4 revenue",
            "value": "$1.095B up 7% YoY",
            "url": "https://finance.yahoo.com/news/akamai-technologies-q4-earnings-call-011249913.html"
          }
        ]
      },
      {
        "type": "deep_dive",
        "heading": "Key Catalysts & Risk Factors",
        "content": "Catalysts are strong growth in security business and AI inference cloud. But margin pressure risk rose due to expected capex increase. Being sensitive to interest rate moves, macro uncertainty also adds to risks.",
        "claims": [
          {
            "what": "2026 EPS guidance",
            "value": "$6.20-$7.20 below $7.29 exp",
            "url": "https://www.tikr.com/blog/akamai-technologies-stock-sinks-14-on-profit-outlook-heres-what-changed-after-q4"
          }
        ]
      },
      {
        "type": "news_talk",
        "heading": "Recent news talk & Developments",
        "content": "Headline is 'Akamai beats earnings but disappoints on guidance.' Investors reacted coldly to news about raising capex for AI investment. Institutional data isn’t out yet but we see large sell-off traces.",
        "claims": [
          {
            "what": "Q4 non-GAAP EPS",
            "value": "$1.84 up 11% YoY",
            "url": "https://finance.yahoo.com/news/akamai-technologies-q4-earnings-call-011249913.html"
          }
        ]
      },
      {
        "type": "flow_talk",
        "heading": "Institutional & Insider Activity",
        "content": "Trading volume surged massively vs usual. Large institutional selling pressure seems strong. No insider info yet, but following whale moves is good during sharp drops.",
        "claims": [
          {
            "what": "Capex Q4",
            "value": "$154M 14% of revenue",
            "url": "https://finance.yahoo.com/news/akamai-technologies-q4-earnings-call-011249913.html"
          }
        ]
      },
      {
        "type": "game_plan",
        "heading": "Investment Plan (3–12 Months)",
        "bull_case": "If guidance is exceeded, re-rating is possible via AI cloud scaling. Continued strong security sales growth could push past $100.",
        "bear_case": "If capex burden grows, margins shrink, and if tech rotation drags on, the stock could fall further.",
        "strategy": "Full bet now is risky. Enter in 10% chunks during oversold phases and buy on rebound signals. In one line? Watch first, then average down timing.",
        "claims": [
          {
            "what": "2026 revenue guide",
            "value": "$4.4B-$4.5B 5-8% growth",
            "url": "https://finance.yahoo.com/news/akamai-technologies-q4-earnings-call-011249913.html"
          }
        ]
      }
    ],
    "faq": [
      {
        "question": "Earnings were good, so why is it falling? ",
        "answer": "Guidance missed expectations. Investors see higher capex as more money going out."
      },
      {
        "question": "Is it okay to buy now?",
        "answer": "It may fall more, so wait for a rebound. Keep an eye if it goes below $80."
      }
    ]
  },
  "images": {
    "cover": {
      "prompt": "Cinematic 3D illustration of a dramatic stock chart plunging with Akamai logo, dark stormy clouds over server data centers, glowing red sell signals, high contrast financial thriller vibe."
    }
  },
  "chart": {
    "ticker": "AKAM",
    "chart_filename": "akam-earnings-drop-guidance-cut-20260223_inner.webp",
    "chart_path": "D:\\\\n8n_local\\\\market-drip\\\\public\\\\posts\\\\img\\akam-earnings-drop-guidance-cut-20260223_inner.webp",
    "analysis": "**Technical:** Below 20-day MA (Bearish trend)\\n\\n**Sentiment:** RSI 45.5 (Neutral zone)\\n\\n**Key Range:** 1-month High $113.50, Low $89.86\\n\\n**Volume:** 15.78M (3.13x vs 20D avg)\\n\\n**Analyst targets:** Mean $108.16 (+14.9%) / Median $110.00 (Range $72.00–$134.00)",
    "image_alt": "AKAM stock chart as of 2026-02-20: close $94.17 (-14.07%), RSI(14) 45.5, 1-month range $89.9–$113.5.",
    "image_caption": "AKAM (2026-02-20): Bearish tone (below 20-day MA); Close $94.17 (-14.07%), RSI(14) 45.5."
  }
}